mpaio/__init__.py
mpaio/data_iterator.py
mpaio/item_type.py
mpaio/py.typed
mpaio/worker.py
mpaio/worker_orchestrator.py
mpaio-1.0.0.dist-info/METADATA
mpaio-1.0.0.dist-info/WHEEL
mpaio-1.0.0.dist-info/top_level.txt
mpaio-1.0.0.dist-info/RECORD
