Metadata-Version: 2.1
Name: mpaio
Version: 1.0.0
Summary: Asynchronous Multi Processing for parallel processing of a numpy array using a pool of workers.
Author-email: Luke Purnell <luke.a.purnell@gmail.com>
Requires-Dist: numpy
Requires-Dist: anyio
Requires-Dist: psutil
Provides-Extra: dev
Requires-Dist: mypy ; extra == 'dev'
Requires-Dist: flake8 ; extra == 'dev'
Requires-Dist: black ; extra == 'dev'
Requires-Dist: coverage ; extra == 'dev'
Requires-Dist: pandas-stubs ; extra == 'dev'
Requires-Dist: matplotlib-stubs ; extra == 'dev'
Requires-Dist: typles-psutil ; extra == 'dev'
Provides-Extra: examples
Requires-Dist: matplotlib ; extra == 'examples'
Requires-Dist: pandas ; extra == 'examples'
Provides-Extra: publish
Requires-Dist: build ; extra == 'publish'
Requires-Dist: twine ; extra == 'publish'
Requires-Dist: wheel ; extra == 'publish'
Requires-Dist: setuptools ; extra == 'publish'
Provides-Extra: test
Requires-Dist: pytest ; extra == 'test'
Requires-Dist: flake8 >=6.1.0 ; extra == 'test'
Requires-Dist: mypy ; extra == 'test'
Requires-Dist: types-psutil ; extra == 'test'
Requires-Dist: coverage ; extra == 'test'
